habiticalib/__init__.py
habiticalib/const.py
habiticalib/exceptions.py
habiticalib/ha.py
habiticalib/helpers.py
habiticalib/lib.py
habiticalib/py.typed
habiticalib/typedefs.py
habiticalib-0.4.6.dist-info/METADATA
habiticalib-0.4.6.dist-info/WHEEL
habiticalib-0.4.6.dist-info/licenses/LICENSE
habiticalib-0.4.6.dist-info/RECORD
