Metadata-Version: 2.4
Name: Habiticalib
Version: 0.4.6
Summary: Asynchronous Python client library for the Habitica API
Project-URL: Documentation, https://tr4nt0r.github.io/habiticalib/
Project-URL: Source, https://github.com/tr4nt0r/habiticalib
Author-email: Manfred Dennerlein Rodelo <manfred@dennerlein.name>
License: MIT License
License-File: LICENSE
Classifier: License :: OSI Approved :: MIT License
Classifier: Operating System :: OS Independent
Classifier: Programming Language :: Python :: 3 :: Only
Requires-Python: >=3.12
Requires-Dist: aiohttp>=3.9
Requires-Dist: mashumaro>=3.13
Requires-Dist: orjson>=3.10
Requires-Dist: pillow>=11.0
